[
  {
    "name": "Potayto",
    "rank": "Overlord",
    "vocation": "Master Sorcerer",
    "level": 466,
    "previousLevel": 466,
    "baselineLevel": 466,
    "baselineDate": "2026-03-30",
    "levelGain": 0,
    "snapshotDate": "2026-03-31",
    "snapshotAt": "2026-03-31T04:59:09.852Z",
    "status": "offline",
    "skillHighlights": {
      "magic": {
        "rank": 134,
        "value": 116,
        "label": "Magic Level"
      }
    },
    "primaryHighscore": {
      "category": "magic",
      "label": "Magic Level",
      "rank": 134,
      "value": 116
    }
  },
  {
    "name": "Dike Arrois",
    "rank": "Field Marshal",
    "vocation": "Elite Knight",
    "level": 927,
    "previousLevel": 927,
    "baselineLevel": 927,
    "baselineDate": "2026-03-30",
    "levelGain": 0,
    "snapshotDate": "2026-03-31",
    "snapshotAt": "2026-03-31T04:59:09.852Z",
    "status": "offline",
    "skillHighlights": {
      "club": {
        "rank": 20,
        "value": 123,
        "label": "Club Fighting"
      }
    },
    "primaryHighscore": {
      "category": "club",
      "label": "Club Fighting",
      "rank": 20,
      "value": 123
    }
  },
  {
    "name": "Indio Grilo Machucado",
    "rank": "Field Marshal",
    "vocation": "Elite Knight",
    "level": 925,
    "previousLevel": 925,
    "baselineLevel": 925,
    "baselineDate": "2026-03-30",
    "levelGain": 0,
    "snapshotDate": "2026-03-31",
    "snapshotAt": "2026-03-31T04:59:09.852Z",
    "status": "offline",
    "skillHighlights": {
      "sword": {
        "rank": 33,
        "value": 123,
        "label": "Sword Fighting"
      }
    },
    "primaryHighscore": {
      "category": "sword",
      "label": "Sword Fighting",
      "rank": 33,
      "value": 123
    }
  },
  {
    "name": "Lexus Shoter",
    "rank": "Field Marshal",
    "vocation": "Royal Paladin",
    "level": 750,
    "previousLevel": 750,
    "baselineLevel": 750,
    "baselineDate": "2026-03-30",
    "levelGain": 0,
    "snapshotDate": "2026-03-31",
    "snapshotAt": "2026-03-31T04:59:09.852Z",
    "status": "offline",
    "skillHighlights": {
      "distance": {
        "rank": 102,
        "value": 124,
        "label": "Distance Fighting"
      }
    },
    "primaryHighscore": {
      "category": "distance",
      "label": "Distance Fighting",
      "rank": 102,
      "value": 124
    }
  },
  {
    "name": "Protetor Carinhoso",
    "rank": "Field Marshal",
    "vocation": "Elite Knight",
    "level": 797,
    "previousLevel": 797,
    "baselineLevel": 797,
    "baselineDate": "2026-03-30",
    "levelGain": 0,
    "snapshotDate": "2026-03-31",
    "snapshotAt": "2026-03-31T04:59:09.852Z",
    "status": "online",
    "skillHighlights": {
      "sword": {
        "rank": 97,
        "value": 118,
        "label": "Sword Fighting"
      }
    },
    "primaryHighscore": {
      "category": "sword",
      "label": "Sword Fighting",
      "rank": 97,
      "value": 118
    }
  },
  {
    "name": "Saint Kaelor",
    "rank": "Field Marshal",
    "vocation": "Royal Paladin",
    "level": 165,
    "previousLevel": 164,
    "baselineLevel": 164,
    "baselineDate": "2026-03-30",
    "levelGain": 1,
    "snapshotDate": "2026-03-31",
    "snapshotAt": "2026-03-31T04:59:09.852Z",
    "status": "offline",
    "skillHighlights": {
      "distance": {
        "rank": 280,
        "value": 119,
        "label": "Distance Fighting"
      }
    },
    "primaryHighscore": {
      "category": "distance",
      "label": "Distance Fighting",
      "rank": 280,
      "value": 119
    }
  },
  {
    "name": "Zycken",
    "rank": "Field Marshal",
    "vocation": "Royal Paladin",
    "level": 1295,
    "previousLevel": 1295,
    "baselineLevel": 1295,
    "baselineDate": "2026-03-30",
    "levelGain": 0,
    "snapshotDate": "2026-03-31",
    "snapshotAt": "2026-03-31T04:59:09.852Z",
    "status": "online",
    "skillHighlights": {
      "distance": {
        "rank": 27,
        "value": 130,
        "label": "Distance Fighting"
      }
    },
    "primaryHighscore": {
      "category": "distance",
      "label": "Distance Fighting",
      "rank": 27,
      "value": 130
    }
  },
  {
    "name": "Emahyak",
    "rank": "Combat Sustainer",
    "vocation": "Master Sorcerer",
    "level": 122,
    "previousLevel": 122,
    "baselineLevel": 122,
    "baselineDate": "2026-03-30",
    "levelGain": 0,
    "snapshotDate": "2026-03-31",
    "snapshotAt": "2026-03-31T04:59:09.852Z",
    "status": "offline",
    "skillHighlights": {},
    "primaryHighscore": null
  },
  {
    "name": "Lexus Heals",
    "rank": "Combat Sustainer",
    "vocation": "Elder Druid",
    "level": 61,
    "previousLevel": 61,
    "baselineLevel": 61,
    "baselineDate": "2026-03-30",
    "levelGain": 0,
    "snapshotDate": "2026-03-31",
    "snapshotAt": "2026-03-31T04:59:09.852Z",
    "status": "offline",
    "skillHighlights": {},
    "primaryHighscore": null
  },
  {
    "name": "Locked Forever",
    "rank": "Combat Sustainer",
    "vocation": "Elite Knight",
    "level": 145,
    "previousLevel": 145,
    "baselineLevel": 145,
    "baselineDate": "2026-03-30",
    "levelGain": 0,
    "snapshotDate": "2026-03-31",
    "snapshotAt": "2026-03-31T04:59:09.852Z",
    "status": "offline",
    "skillHighlights": {
      "sword": {
        "rank": 903,
        "value": 100,
        "label": "Sword Fighting"
      }
    },
    "primaryHighscore": {
      "category": "sword",
      "label": "Sword Fighting",
      "rank": 903,
      "value": 100
    }
  },
  {
    "name": "Mimosa com Narguet",
    "rank": "Combat Sustainer",
    "vocation": "Elder Druid",
    "level": 95,
    "previousLevel": 95,
    "baselineLevel": 95,
    "baselineDate": "2026-03-30",
    "levelGain": 0,
    "snapshotDate": "2026-03-31",
    "snapshotAt": "2026-03-31T04:59:09.852Z",
    "status": "offline",
    "skillHighlights": {},
    "primaryHighscore": null
  },
  {
    "name": "Mokiie",
    "rank": "Combat Sustainer",
    "vocation": "Master Sorcerer",
    "level": 130,
    "previousLevel": 130,
    "baselineLevel": 130,
    "baselineDate": "2026-03-30",
    "levelGain": 0,
    "snapshotDate": "2026-03-31",
    "snapshotAt": "2026-03-31T04:59:09.852Z",
    "status": "offline",
    "skillHighlights": {},
    "primaryHighscore": null
  },
  {
    "name": "Potayto Sio",
    "rank": "Combat Sustainer",
    "vocation": "Elder Druid",
    "level": 282,
    "previousLevel": 282,
    "baselineLevel": 282,
    "baselineDate": "2026-03-30",
    "levelGain": 0,
    "snapshotDate": "2026-03-31",
    "snapshotAt": "2026-03-31T04:59:09.852Z",
    "status": "offline",
    "skillHighlights": {},
    "primaryHighscore": null
  },
  {
    "name": "Xitao do Xororo",
    "rank": "Combat Sustainer",
    "vocation": "Elder Druid",
    "level": 29,
    "previousLevel": 29,
    "baselineLevel": 29,
    "baselineDate": "2026-03-30",
    "levelGain": 0,
    "snapshotDate": "2026-03-31",
    "snapshotAt": "2026-03-31T04:59:09.852Z",
    "status": "offline",
    "skillHighlights": {},
    "primaryHighscore": null
  },
  {
    "name": "Big Bugalu",
    "rank": "Apex Guardian",
    "vocation": "Royal Paladin",
    "level": 702,
    "previousLevel": 702,
    "baselineLevel": 702,
    "baselineDate": "2026-03-30",
    "levelGain": 0,
    "snapshotDate": "2026-03-31",
    "snapshotAt": "2026-03-31T04:59:09.852Z",
    "status": "offline",
    "skillHighlights": {
      "distance": {
        "rank": 148,
        "value": 122,
        "label": "Distance Fighting"
      }
    },
    "primaryHighscore": {
      "category": "distance",
      "label": "Distance Fighting",
      "rank": 148,
      "value": 122
    }
  },
  {
    "name": "Claudio Bojanha dois",
    "rank": "Apex Guardian",
    "vocation": "Royal Paladin",
    "level": 691,
    "previousLevel": 691,
    "baselineLevel": 691,
    "baselineDate": "2026-03-30",
    "levelGain": 0,
    "snapshotDate": "2026-03-31",
    "snapshotAt": "2026-03-31T04:59:09.852Z",
    "status": "offline",
    "skillHighlights": {
      "distance": {
        "rank": 122,
        "value": 123,
        "label": "Distance Fighting"
      }
    },
    "primaryHighscore": {
      "category": "distance",
      "label": "Distance Fighting",
      "rank": 122,
      "value": 123
    }
  },
  {
    "name": "Hokage Clarinha",
    "rank": "Apex Guardian",
    "vocation": "Elite Knight",
    "level": 662,
    "previousLevel": 662,
    "baselineLevel": 662,
    "baselineDate": "2026-03-30",
    "levelGain": 0,
    "snapshotDate": "2026-03-31",
    "snapshotAt": "2026-03-31T04:59:09.852Z",
    "status": "offline",
    "skillHighlights": {
      "club": {
        "rank": 73,
        "value": 116,
        "label": "Club Fighting"
      }
    },
    "primaryHighscore": {
      "category": "club",
      "label": "Club Fighting",
      "rank": 73,
      "value": 116
    }
  },
  {
    "name": "Luna Nightwitch",
    "rank": "Apex Guardian",
    "vocation": "Elite Knight",
    "level": 681,
    "previousLevel": 681,
    "baselineLevel": 681,
    "baselineDate": "2026-03-30",
    "levelGain": 0,
    "snapshotDate": "2026-03-31",
    "snapshotAt": "2026-03-31T04:59:09.852Z",
    "status": "offline",
    "skillHighlights": {
      "sword": {
        "rank": 97,
        "value": 118,
        "label": "Sword Fighting"
      }
    },
    "primaryHighscore": {
      "category": "sword",
      "label": "Sword Fighting",
      "rank": 97,
      "value": 118
    }
  },
  {
    "name": "Seven Madlife",
    "rank": "Apex Guardian",
    "vocation": "Master Sorcerer",
    "level": 658,
    "previousLevel": 658,
    "baselineLevel": 658,
    "baselineDate": "2026-03-30",
    "levelGain": 0,
    "snapshotDate": "2026-03-31",
    "snapshotAt": "2026-03-31T04:59:09.852Z",
    "status": "offline",
    "skillHighlights": {
      "magic": {
        "rank": 195,
        "value": 112,
        "label": "Magic Level"
      }
    },
    "primaryHighscore": {
      "category": "magic",
      "label": "Magic Level",
      "rank": 195,
      "value": 112
    }
  },
  {
    "name": "Sir Alonta",
    "rank": "Apex Guardian",
    "vocation": "Elite Knight",
    "level": 765,
    "previousLevel": 765,
    "baselineLevel": 765,
    "baselineDate": "2026-03-30",
    "levelGain": 0,
    "snapshotDate": "2026-03-31",
    "snapshotAt": "2026-03-31T04:59:09.852Z",
    "status": "offline",
    "skillHighlights": {
      "axe": {
        "rank": 16,
        "value": 124,
        "label": "Axe Fighting"
      },
      "club": {
        "rank": 30,
        "value": 121,
        "label": "Club Fighting"
      }
    },
    "primaryHighscore": {
      "category": "axe",
      "label": "Axe Fighting",
      "rank": 16,
      "value": 124
    }
  },
  {
    "name": "Skillo da Selva",
    "rank": "Apex Guardian",
    "vocation": "Elder Druid",
    "level": 857,
    "previousLevel": 857,
    "baselineLevel": 857,
    "baselineDate": "2026-03-30",
    "levelGain": 0,
    "snapshotDate": "2026-03-31",
    "snapshotAt": "2026-03-31T04:59:09.852Z",
    "status": "offline",
    "skillHighlights": {
      "magic": {
        "rank": 170,
        "value": 114,
        "label": "Magic Level"
      }
    },
    "primaryHighscore": {
      "category": "magic",
      "label": "Magic Level",
      "rank": 170,
      "value": 114
    }
  },
  {
    "name": "Vitinho Cepowisks",
    "rank": "Apex Guardian",
    "vocation": "Elder Druid",
    "level": 762,
    "previousLevel": 761,
    "baselineLevel": 761,
    "baselineDate": "2026-03-30",
    "levelGain": 1,
    "snapshotDate": "2026-03-31",
    "snapshotAt": "2026-03-31T04:59:09.852Z",
    "status": "offline",
    "skillHighlights": {
      "magic": {
        "rank": 134,
        "value": 116,
        "label": "Magic Level"
      }
    },
    "primaryHighscore": {
      "category": "magic",
      "label": "Magic Level",
      "rank": 134,
      "value": 116
    }
  },
  {
    "name": "Asgore Fullagado",
    "rank": "Primal Summoner",
    "vocation": "Paladin",
    "level": 201,
    "previousLevel": 201,
    "baselineLevel": 201,
    "baselineDate": "2026-03-30",
    "levelGain": 0,
    "snapshotDate": "2026-03-31",
    "snapshotAt": "2026-03-31T04:59:09.852Z",
    "status": "offline",
    "skillHighlights": {
      "distance": {
        "rank": 557,
        "value": 115,
        "label": "Distance Fighting"
      }
    },
    "primaryHighscore": {
      "category": "distance",
      "label": "Distance Fighting",
      "rank": 557,
      "value": 115
    }
  },
  {
    "name": "Biscoito Babado",
    "rank": "Primal Summoner",
    "vocation": "Master Sorcerer",
    "level": 362,
    "previousLevel": 362,
    "baselineLevel": 362,
    "baselineDate": "2026-03-30",
    "levelGain": 0,
    "snapshotDate": "2026-03-31",
    "snapshotAt": "2026-03-31T04:59:09.852Z",
    "status": "offline",
    "skillHighlights": {
      "magic": {
        "rank": 590,
        "value": 98,
        "label": "Magic Level"
      }
    },
    "primaryHighscore": {
      "category": "magic",
      "label": "Magic Level",
      "rank": 590,
      "value": 98
    }
  },
  {
    "name": "Daveigavt",
    "rank": "Primal Summoner",
    "vocation": "Royal Paladin",
    "level": 453,
    "previousLevel": 452,
    "baselineLevel": 452,
    "baselineDate": "2026-03-30",
    "levelGain": 1,
    "snapshotDate": "2026-03-31",
    "snapshotAt": "2026-03-31T04:59:09.852Z",
    "status": "offline",
    "skillHighlights": {
      "distance": {
        "rank": 474,
        "value": 116,
        "label": "Distance Fighting"
      }
    },
    "primaryHighscore": {
      "category": "distance",
      "label": "Distance Fighting",
      "rank": 474,
      "value": 116
    }
  },
  {
    "name": "Is Maik",
    "rank": "Primal Summoner",
    "vocation": "Elite Knight",
    "level": 330,
    "previousLevel": 330,
    "baselineLevel": 330,
    "baselineDate": "2026-03-30",
    "levelGain": 0,
    "snapshotDate": "2026-03-31",
    "snapshotAt": "2026-03-31T04:59:09.852Z",
    "status": "offline",
    "skillHighlights": {
      "sword": {
        "rank": 156,
        "value": 115,
        "label": "Sword Fighting"
      }
    },
    "primaryHighscore": {
      "category": "sword",
      "label": "Sword Fighting",
      "rank": 156,
      "value": 115
    }
  },
  {
    "name": "Kow Hife",
    "rank": "Primal Summoner",
    "vocation": "Elder Druid",
    "level": 364,
    "previousLevel": 364,
    "baselineLevel": 364,
    "baselineDate": "2026-03-30",
    "levelGain": 0,
    "snapshotDate": "2026-03-31",
    "snapshotAt": "2026-03-31T04:59:09.852Z",
    "status": "offline",
    "skillHighlights": {
      "magic": {
        "rank": 726,
        "value": 95,
        "label": "Magic Level"
      }
    },
    "primaryHighscore": {
      "category": "magic",
      "label": "Magic Level",
      "rank": 726,
      "value": 95
    }
  },
  {
    "name": "Mage Kiro",
    "rank": "Primal Summoner",
    "vocation": "Master Sorcerer",
    "level": 526,
    "previousLevel": 526,
    "baselineLevel": 526,
    "baselineDate": "2026-03-30",
    "levelGain": 0,
    "snapshotDate": "2026-03-31",
    "snapshotAt": "2026-03-31T04:59:09.852Z",
    "status": "offline",
    "skillHighlights": {
      "magic": {
        "rank": 392,
        "value": 103,
        "label": "Magic Level"
      }
    },
    "primaryHighscore": {
      "category": "magic",
      "label": "Magic Level",
      "rank": 392,
      "value": 103
    }
  },
  {
    "name": "Pods Cre",
    "rank": "Primal Summoner",
    "vocation": "Royal Paladin",
    "level": 400,
    "previousLevel": 400,
    "baselineLevel": 400,
    "baselineDate": "2026-03-30",
    "levelGain": 0,
    "snapshotDate": "2026-03-31",
    "snapshotAt": "2026-03-31T04:59:09.852Z",
    "status": "offline",
    "skillHighlights": {
      "distance": {
        "rank": 742,
        "value": 113,
        "label": "Distance Fighting"
      }
    },
    "primaryHighscore": {
      "category": "distance",
      "label": "Distance Fighting",
      "rank": 742,
      "value": 113
    }
  },
  {
    "name": "Severo Snappee",
    "rank": "Primal Summoner",
    "vocation": "Master Sorcerer",
    "level": 342,
    "previousLevel": 341,
    "baselineLevel": 341,
    "baselineDate": "2026-03-30",
    "levelGain": 1,
    "snapshotDate": "2026-03-31",
    "snapshotAt": "2026-03-31T04:59:09.852Z",
    "status": "offline",
    "skillHighlights": {
      "magic": {
        "rank": 616,
        "value": 97,
        "label": "Magic Level"
      }
    },
    "primaryHighscore": {
      "category": "magic",
      "label": "Magic Level",
      "rank": 616,
      "value": 97
    }
  },
  {
    "name": "Vinks",
    "rank": "Primal Summoner",
    "vocation": "Elite Knight",
    "level": 374,
    "previousLevel": 374,
    "baselineLevel": 374,
    "baselineDate": "2026-03-30",
    "levelGain": 0,
    "snapshotDate": "2026-03-31",
    "snapshotAt": "2026-03-31T04:59:09.852Z",
    "status": "offline",
    "skillHighlights": {
      "axe": {
        "rank": 308,
        "value": 108,
        "label": "Axe Fighting"
      }
    },
    "primaryHighscore": {
      "category": "axe",
      "label": "Axe Fighting",
      "rank": 308,
      "value": 108
    }
  },
  {
    "name": "Witch Nobeta",
    "rank": "Primal Summoner",
    "vocation": "Exalted Monk",
    "level": 308,
    "previousLevel": 308,
    "baselineLevel": 308,
    "baselineDate": "2026-03-30",
    "levelGain": 0,
    "snapshotDate": "2026-03-31",
    "snapshotAt": "2026-03-31T04:59:09.852Z",
    "status": "offline",
    "skillHighlights": {
      "fist": {
        "rank": 378,
        "value": 95,
        "label": "Fist Fighting"
      }
    },
    "primaryHighscore": {
      "category": "fist",
      "label": "Fist Fighting",
      "rank": 378,
      "value": 95
    }
  },
  {
    "name": "Amiane Keny",
    "rank": "Rising Sentinel",
    "vocation": "Royal Paladin",
    "level": 150,
    "previousLevel": 150,
    "baselineLevel": 150,
    "baselineDate": "2026-03-30",
    "levelGain": 0,
    "snapshotDate": "2026-03-31",
    "snapshotAt": "2026-03-31T04:59:09.852Z",
    "status": "offline",
    "skillHighlights": {},
    "primaryHighscore": null
  },
  {
    "name": "Asgore Lessus",
    "rank": "Rising Sentinel",
    "vocation": "None",
    "level": 2,
    "previousLevel": 2,
    "baselineLevel": 2,
    "baselineDate": "2026-03-30",
    "levelGain": 0,
    "snapshotDate": "2026-03-31",
    "snapshotAt": "2026-03-31T04:59:09.852Z",
    "status": "offline",
    "skillHighlights": {},
    "primaryHighscore": null
  },
  {
    "name": "Cadu Uzabunnda",
    "rank": "Rising Sentinel",
    "vocation": "Elite Knight",
    "level": 56,
    "previousLevel": 56,
    "baselineLevel": 56,
    "baselineDate": "2026-03-30",
    "levelGain": 0,
    "snapshotDate": "2026-03-31",
    "snapshotAt": "2026-03-31T04:59:09.852Z",
    "status": "offline",
    "skillHighlights": {},
    "primaryHighscore": null
  },
  {
    "name": "Dike Fibrado",
    "rank": "Rising Sentinel",
    "vocation": "Elite Knight",
    "level": 38,
    "previousLevel": 38,
    "baselineLevel": 38,
    "baselineDate": "2026-03-30",
    "levelGain": 0,
    "snapshotDate": "2026-03-31",
    "snapshotAt": "2026-03-31T04:59:09.852Z",
    "status": "offline",
    "skillHighlights": {
      "axe": {
        "rank": 308,
        "value": 108,
        "label": "Axe Fighting"
      }
    },
    "primaryHighscore": {
      "category": "axe",
      "label": "Axe Fighting",
      "rank": 308,
      "value": 108
    }
  },
  {
    "name": "Doule Lana",
    "rank": "Rising Sentinel",
    "vocation": "Elite Knight",
    "level": 54,
    "previousLevel": 54,
    "baselineLevel": 54,
    "baselineDate": "2026-03-30",
    "levelGain": 0,
    "snapshotDate": "2026-03-31",
    "snapshotAt": "2026-03-31T04:59:09.852Z",
    "status": "offline",
    "skillHighlights": {
      "axe": {
        "rank": 271,
        "value": 109,
        "label": "Axe Fighting"
      }
    },
    "primaryHighscore": {
      "category": "axe",
      "label": "Axe Fighting",
      "rank": 271,
      "value": 109
    }
  },
  {
    "name": "Nonota",
    "rank": "Rising Sentinel",
    "vocation": "Monk",
    "level": 15,
    "previousLevel": 15,
    "baselineLevel": 15,
    "baselineDate": "2026-03-30",
    "levelGain": 0,
    "snapshotDate": "2026-03-31",
    "snapshotAt": "2026-03-31T04:59:09.852Z",
    "status": "offline",
    "skillHighlights": {},
    "primaryHighscore": null
  },
  {
    "name": "Valeu tamojunto",
    "rank": "Rising Sentinel",
    "vocation": "Elite Knight",
    "level": 163,
    "previousLevel": 163,
    "baselineLevel": 163,
    "baselineDate": "2026-03-30",
    "levelGain": 0,
    "snapshotDate": "2026-03-31",
    "snapshotAt": "2026-03-31T04:59:09.852Z",
    "status": "offline",
    "skillHighlights": {
      "axe": {
        "rank": 186,
        "value": 111,
        "label": "Axe Fighting"
      }
    },
    "primaryHighscore": {
      "category": "axe",
      "label": "Axe Fighting",
      "rank": 186,
      "value": 111
    }
  },
  {
    "name": "Walord Canelinha",
    "rank": "Rising Sentinel",
    "vocation": "Elder Druid",
    "level": 35,
    "previousLevel": 35,
    "baselineLevel": 35,
    "baselineDate": "2026-03-30",
    "levelGain": 0,
    "snapshotDate": "2026-03-31",
    "snapshotAt": "2026-03-31T04:59:09.852Z",
    "status": "offline",
    "skillHighlights": {},
    "primaryHighscore": null
  },
  {
    "name": "Badlius",
    "rank": "Provisional Soul",
    "vocation": "Master Sorcerer",
    "level": 419,
    "previousLevel": 419,
    "baselineLevel": 419,
    "baselineDate": "2026-03-30",
    "levelGain": 0,
    "snapshotDate": "2026-03-31",
    "snapshotAt": "2026-03-31T04:59:09.852Z",
    "status": "online",
    "skillHighlights": {
      "magic": {
        "rank": 461,
        "value": 101,
        "label": "Magic Level"
      }
    },
    "primaryHighscore": {
      "category": "magic",
      "label": "Magic Level",
      "rank": 461,
      "value": 101
    }
  },
  {
    "name": "Bombaschick",
    "rank": "Provisional Soul",
    "vocation": "Elite Knight",
    "level": 214,
    "previousLevel": 214,
    "baselineLevel": 214,
    "baselineDate": "2026-03-30",
    "levelGain": 0,
    "snapshotDate": "2026-03-31",
    "snapshotAt": "2026-03-31T04:59:09.852Z",
    "status": "offline",
    "skillHighlights": {
      "club": {
        "rank": 489,
        "value": 104,
        "label": "Club Fighting"
      }
    },
    "primaryHighscore": {
      "category": "club",
      "label": "Club Fighting",
      "rank": 489,
      "value": 104
    }
  },
  {
    "name": "Derekaunn",
    "rank": "Provisional Soul",
    "vocation": "Royal Paladin",
    "level": 214,
    "previousLevel": 214,
    "baselineLevel": 214,
    "baselineDate": "2026-03-30",
    "levelGain": 0,
    "snapshotDate": "2026-03-31",
    "snapshotAt": "2026-03-31T04:59:09.852Z",
    "status": "offline",
    "skillHighlights": {},
    "primaryHighscore": null
  },
  {
    "name": "Deyvcabelinho",
    "rank": "Provisional Soul",
    "vocation": "Master Sorcerer",
    "level": 103,
    "previousLevel": 103,
    "baselineLevel": 103,
    "baselineDate": "2026-03-30",
    "levelGain": 0,
    "snapshotDate": "2026-03-31",
    "snapshotAt": "2026-03-31T04:59:09.852Z",
    "status": "offline",
    "skillHighlights": {},
    "primaryHighscore": null
  },
  {
    "name": "Ed Galoucura",
    "rank": "Provisional Soul",
    "vocation": "Druid",
    "level": 8,
    "previousLevel": 8,
    "baselineLevel": 8,
    "baselineDate": "2026-03-30",
    "levelGain": 0,
    "snapshotDate": "2026-03-31",
    "snapshotAt": "2026-03-31T04:59:09.852Z",
    "status": "offline",
    "skillHighlights": {},
    "primaryHighscore": null
  },
  {
    "name": "Florzinha Love",
    "rank": "Provisional Soul",
    "vocation": "Elite Knight",
    "level": 800,
    "previousLevel": 800,
    "baselineLevel": 800,
    "baselineDate": "2026-03-30",
    "levelGain": 0,
    "snapshotDate": "2026-03-31",
    "snapshotAt": "2026-03-31T04:59:09.852Z",
    "status": "offline",
    "skillHighlights": {
      "sword": {
        "rank": 18,
        "value": 126,
        "label": "Sword Fighting"
      }
    },
    "primaryHighscore": {
      "category": "sword",
      "label": "Sword Fighting",
      "rank": 18,
      "value": 126
    }
  },
  {
    "name": "Isakiinn",
    "rank": "Provisional Soul",
    "vocation": "Master Sorcerer",
    "level": 101,
    "previousLevel": 101,
    "baselineLevel": 101,
    "baselineDate": "2026-03-30",
    "levelGain": 0,
    "snapshotDate": "2026-03-31",
    "snapshotAt": "2026-03-31T04:59:09.852Z",
    "status": "offline",
    "skillHighlights": {},
    "primaryHighscore": null
  },
  {
    "name": "Javaahh",
    "rank": "Provisional Soul",
    "vocation": "Royal Paladin",
    "level": 215,
    "previousLevel": 215,
    "baselineLevel": 215,
    "baselineDate": "2026-03-30",
    "levelGain": 0,
    "snapshotDate": "2026-03-31",
    "snapshotAt": "2026-03-31T04:59:09.852Z",
    "status": "offline",
    "skillHighlights": {
      "distance": {
        "rank": 388,
        "value": 117,
        "label": "Distance Fighting"
      }
    },
    "primaryHighscore": {
      "category": "distance",
      "label": "Distance Fighting",
      "rank": 388,
      "value": 117
    }
  },
  {
    "name": "Liocrismar Junior",
    "rank": "Provisional Soul",
    "vocation": "Elite Knight",
    "level": 260,
    "previousLevel": 260,
    "baselineLevel": 260,
    "baselineDate": "2026-03-30",
    "levelGain": 0,
    "snapshotDate": "2026-03-31",
    "snapshotAt": "2026-03-31T04:59:09.852Z",
    "status": "offline",
    "skillHighlights": {
      "axe": {
        "rank": 384,
        "value": 106,
        "label": "Axe Fighting"
      }
    },
    "primaryHighscore": {
      "category": "axe",
      "label": "Axe Fighting",
      "rank": 384,
      "value": 106
    }
  },
  {
    "name": "Loshh",
    "rank": "Provisional Soul",
    "vocation": "Royal Paladin",
    "level": 545,
    "previousLevel": 545,
    "baselineLevel": 545,
    "baselineDate": "2026-03-30",
    "levelGain": 0,
    "snapshotDate": "2026-03-31",
    "snapshotAt": "2026-03-31T04:59:09.852Z",
    "status": "offline",
    "skillHighlights": {
      "distance": {
        "rank": 148,
        "value": 122,
        "label": "Distance Fighting"
      }
    },
    "primaryHighscore": {
      "category": "distance",
      "label": "Distance Fighting",
      "rank": 148,
      "value": 122
    }
  },
  {
    "name": "Lukinha Modtanker",
    "rank": "Provisional Soul",
    "vocation": "Elite Knight",
    "level": 422,
    "previousLevel": 422,
    "baselineLevel": 422,
    "baselineDate": "2026-03-30",
    "levelGain": 0,
    "snapshotDate": "2026-03-31",
    "snapshotAt": "2026-03-31T04:59:09.852Z",
    "status": "offline",
    "skillHighlights": {
      "club": {
        "rank": 109,
        "value": 114,
        "label": "Club Fighting"
      }
    },
    "primaryHighscore": {
      "category": "club",
      "label": "Club Fighting",
      "rank": 109,
      "value": 114
    }
  },
  {
    "name": "Mago Morais",
    "rank": "Provisional Soul",
    "vocation": "Elite Knight",
    "level": 229,
    "previousLevel": 229,
    "baselineLevel": 229,
    "baselineDate": "2026-03-30",
    "levelGain": 0,
    "snapshotDate": "2026-03-31",
    "snapshotAt": "2026-03-31T04:59:09.852Z",
    "status": "offline",
    "skillHighlights": {},
    "primaryHighscore": null
  },
  {
    "name": "Scorpion Reborn",
    "rank": "Provisional Soul",
    "vocation": "Elite Knight",
    "level": 1065,
    "previousLevel": 1065,
    "baselineLevel": 1065,
    "baselineDate": "2026-03-30",
    "levelGain": 0,
    "snapshotDate": "2026-03-31",
    "snapshotAt": "2026-03-31T04:59:09.852Z",
    "status": "offline",
    "skillHighlights": {
      "axe": {
        "rank": 22,
        "value": 122,
        "label": "Axe Fighting"
      }
    },
    "primaryHighscore": {
      "category": "axe",
      "label": "Axe Fighting",
      "rank": 22,
      "value": 122
    }
  },
  {
    "name": "Wild Serenity",
    "rank": "Provisional Soul",
    "vocation": "Elder Druid",
    "level": 354,
    "previousLevel": 354,
    "baselineLevel": 354,
    "baselineDate": "2026-03-30",
    "levelGain": 0,
    "snapshotDate": "2026-03-31",
    "snapshotAt": "2026-03-31T04:59:09.852Z",
    "status": "offline",
    "skillHighlights": {
      "magic": {
        "rank": 674,
        "value": 96,
        "label": "Magic Level"
      }
    },
    "primaryHighscore": {
      "category": "magic",
      "label": "Magic Level",
      "rank": 674,
      "value": 96
    }
  },
  {
    "name": "Xandzudo",
    "rank": "Provisional Soul",
    "vocation": "Exalted Monk",
    "level": 336,
    "previousLevel": 336,
    "baselineLevel": 336,
    "baselineDate": "2026-03-30",
    "levelGain": 0,
    "snapshotDate": "2026-03-31",
    "snapshotAt": "2026-03-31T04:59:09.852Z",
    "status": "offline",
    "skillHighlights": {
      "fist": {
        "rank": 133,
        "value": 101,
        "label": "Fist Fighting"
      }
    },
    "primaryHighscore": {
      "category": "fist",
      "label": "Fist Fighting",
      "rank": 133,
      "value": 101
    }
  }
]