[
  {
    "name": "Potayto",
    "rank": "Overlord",
    "vocation": "Master Sorcerer",
    "level": 472,
    "previousLevel": 472,
    "baselineLevel": 472,
    "baselineDate": "2026-05-01",
    "levelGain": 0,
    "snapshotDate": "2026-05-02",
    "snapshotAt": "2026-05-02T05:22:29.502Z",
    "status": "online",
    "skillHighlights": {
      "magic": {
        "rank": 142,
        "value": 116,
        "label": "Magic Level"
      }
    },
    "primaryHighscore": {
      "category": "magic",
      "label": "Magic Level",
      "rank": 142,
      "value": 116
    },
    "primarySkillTrend": "none",
    "primarySkillTrendDate": null
  },
  {
    "name": "Dike Arrois",
    "rank": "Field Marshal",
    "vocation": "Elite Knight",
    "level": 950,
    "previousLevel": 948,
    "baselineLevel": 948,
    "baselineDate": "2026-05-01",
    "levelGain": 2,
    "snapshotDate": "2026-05-02",
    "snapshotAt": "2026-05-02T05:22:29.502Z",
    "status": "offline",
    "skillHighlights": {
      "club": {
        "rank": 22,
        "value": 123,
        "label": "Club Fighting"
      }
    },
    "primaryHighscore": {
      "category": "club",
      "label": "Club Fighting",
      "rank": 22,
      "value": 123
    },
    "primarySkillTrend": "none",
    "primarySkillTrendDate": null
  },
  {
    "name": "Golf Sapao Ressuscitado",
    "rank": "Field Marshal",
    "vocation": "Elder Druid",
    "level": 731,
    "previousLevel": 731,
    "baselineLevel": 731,
    "baselineDate": "2026-05-01",
    "levelGain": 0,
    "snapshotDate": "2026-05-02",
    "snapshotAt": "2026-05-02T05:22:29.502Z",
    "status": "online",
    "skillHighlights": {
      "magic": {
        "rank": 220,
        "value": 111,
        "label": "Magic Level"
      }
    },
    "primaryHighscore": {
      "category": "magic",
      "label": "Magic Level",
      "rank": 220,
      "value": 111
    },
    "primarySkillTrend": "none",
    "primarySkillTrendDate": null
  },
  {
    "name": "Indio Grilo Machucado",
    "rank": "Field Marshal",
    "vocation": "Elite Knight",
    "level": 946,
    "previousLevel": 946,
    "baselineLevel": 946,
    "baselineDate": "2026-05-01",
    "levelGain": 0,
    "snapshotDate": "2026-05-02",
    "snapshotAt": "2026-05-02T05:22:29.502Z",
    "status": "online",
    "skillHighlights": {
      "sword": {
        "rank": 35,
        "value": 123,
        "label": "Sword Fighting"
      }
    },
    "primaryHighscore": {
      "category": "sword",
      "label": "Sword Fighting",
      "rank": 35,
      "value": 123
    },
    "primarySkillTrend": "none",
    "primarySkillTrendDate": null
  },
  {
    "name": "Lexus Shoter",
    "rank": "Field Marshal",
    "vocation": "Royal Paladin",
    "level": 756,
    "previousLevel": 756,
    "baselineLevel": 756,
    "baselineDate": "2026-05-01",
    "levelGain": 0,
    "snapshotDate": "2026-05-02",
    "snapshotAt": "2026-05-02T05:22:29.502Z",
    "status": "offline",
    "skillHighlights": {
      "distance": {
        "rank": 103,
        "value": 124,
        "label": "Distance Fighting"
      }
    },
    "primaryHighscore": {
      "category": "distance",
      "label": "Distance Fighting",
      "rank": 103,
      "value": 124
    },
    "primarySkillTrend": "none",
    "primarySkillTrendDate": null
  },
  {
    "name": "Protetor Carinhoso",
    "rank": "Field Marshal",
    "vocation": "Elite Knight",
    "level": 820,
    "previousLevel": 820,
    "baselineLevel": 820,
    "baselineDate": "2026-05-01",
    "levelGain": 0,
    "snapshotDate": "2026-05-02",
    "snapshotAt": "2026-05-02T05:22:29.502Z",
    "status": "offline",
    "skillHighlights": {
      "sword": {
        "rank": 100,
        "value": 118,
        "label": "Sword Fighting"
      }
    },
    "primaryHighscore": {
      "category": "sword",
      "label": "Sword Fighting",
      "rank": 100,
      "value": 118
    },
    "primarySkillTrend": "none",
    "primarySkillTrendDate": null
  },
  {
    "name": "Saint Kaelor",
    "rank": "Field Marshal",
    "vocation": "Paladin",
    "level": 182,
    "previousLevel": 182,
    "baselineLevel": 182,
    "baselineDate": "2026-05-01",
    "levelGain": 0,
    "snapshotDate": "2026-05-02",
    "snapshotAt": "2026-05-02T05:22:29.502Z",
    "status": "offline",
    "skillHighlights": {
      "distance": {
        "rank": 348,
        "value": 118,
        "label": "Distance Fighting"
      }
    },
    "primaryHighscore": {
      "category": "distance",
      "label": "Distance Fighting",
      "rank": 348,
      "value": 118
    },
    "primarySkillTrend": "none",
    "primarySkillTrendDate": null
  },
  {
    "name": "Zycken",
    "rank": "Field Marshal",
    "vocation": "Royal Paladin",
    "level": 1310,
    "previousLevel": 1309,
    "baselineLevel": 1309,
    "baselineDate": "2026-05-01",
    "levelGain": 1,
    "snapshotDate": "2026-05-02",
    "snapshotAt": "2026-05-02T05:22:29.502Z",
    "status": "online",
    "skillHighlights": {
      "distance": {
        "rank": 27,
        "value": 130,
        "label": "Distance Fighting"
      }
    },
    "primaryHighscore": {
      "category": "distance",
      "label": "Distance Fighting",
      "rank": 27,
      "value": 130
    },
    "primarySkillTrend": "none",
    "primarySkillTrendDate": null
  },
  {
    "name": "Emahyak",
    "rank": "Combat Sustainer",
    "vocation": "Master Sorcerer",
    "level": 128,
    "previousLevel": 128,
    "baselineLevel": 128,
    "baselineDate": "2026-05-01",
    "levelGain": 0,
    "snapshotDate": "2026-05-02",
    "snapshotAt": "2026-05-02T05:22:29.502Z",
    "status": "offline",
    "skillHighlights": {},
    "primaryHighscore": null,
    "primarySkillTrend": "none",
    "primarySkillTrendDate": null
  },
  {
    "name": "Lexus Heals",
    "rank": "Combat Sustainer",
    "vocation": "Elder Druid",
    "level": 61,
    "previousLevel": 61,
    "baselineLevel": 61,
    "baselineDate": "2026-05-01",
    "levelGain": 0,
    "snapshotDate": "2026-05-02",
    "snapshotAt": "2026-05-02T05:22:29.502Z",
    "status": "offline",
    "skillHighlights": {},
    "primaryHighscore": null,
    "primarySkillTrend": "none",
    "primarySkillTrendDate": null
  },
  {
    "name": "Locked Forever",
    "rank": "Combat Sustainer",
    "vocation": "Elite Knight",
    "level": 145,
    "previousLevel": 145,
    "baselineLevel": 145,
    "baselineDate": "2026-05-01",
    "levelGain": 0,
    "snapshotDate": "2026-05-02",
    "snapshotAt": "2026-05-02T05:22:29.502Z",
    "status": "offline",
    "skillHighlights": {
      "sword": {
        "rank": 850,
        "value": 101,
        "label": "Sword Fighting"
      }
    },
    "primaryHighscore": {
      "category": "sword",
      "label": "Sword Fighting",
      "rank": 850,
      "value": 101
    },
    "primarySkillTrend": "none",
    "primarySkillTrendDate": null
  },
  {
    "name": "Mimosa com Narguet",
    "rank": "Combat Sustainer",
    "vocation": "Elder Druid",
    "level": 95,
    "previousLevel": 95,
    "baselineLevel": 95,
    "baselineDate": "2026-05-01",
    "levelGain": 0,
    "snapshotDate": "2026-05-02",
    "snapshotAt": "2026-05-02T05:22:29.502Z",
    "status": "offline",
    "skillHighlights": {},
    "primaryHighscore": null,
    "primarySkillTrend": "none",
    "primarySkillTrendDate": null
  },
  {
    "name": "Mokiie",
    "rank": "Combat Sustainer",
    "vocation": "Master Sorcerer",
    "level": 130,
    "previousLevel": 130,
    "baselineLevel": 130,
    "baselineDate": "2026-05-01",
    "levelGain": 0,
    "snapshotDate": "2026-05-02",
    "snapshotAt": "2026-05-02T05:22:29.502Z",
    "status": "offline",
    "skillHighlights": {},
    "primaryHighscore": null,
    "primarySkillTrend": "none",
    "primarySkillTrendDate": null
  },
  {
    "name": "Potayto Sio",
    "rank": "Combat Sustainer",
    "vocation": "Elder Druid",
    "level": 285,
    "previousLevel": 285,
    "baselineLevel": 285,
    "baselineDate": "2026-05-01",
    "levelGain": 0,
    "snapshotDate": "2026-05-02",
    "snapshotAt": "2026-05-02T05:22:29.502Z",
    "status": "offline",
    "skillHighlights": {},
    "primaryHighscore": null,
    "primarySkillTrend": "none",
    "primarySkillTrendDate": null
  },
  {
    "name": "Xitao do Xororo",
    "rank": "Combat Sustainer",
    "vocation": "Elder Druid",
    "level": 30,
    "previousLevel": 30,
    "baselineLevel": 30,
    "baselineDate": "2026-05-01",
    "levelGain": 0,
    "snapshotDate": "2026-05-02",
    "snapshotAt": "2026-05-02T05:22:29.502Z",
    "status": "offline",
    "skillHighlights": {},
    "primaryHighscore": null,
    "primarySkillTrend": "none",
    "primarySkillTrendDate": null
  },
  {
    "name": "Big Bugalu",
    "rank": "Apex Guardian",
    "vocation": "Royal Paladin",
    "level": 709,
    "previousLevel": 707,
    "baselineLevel": 707,
    "baselineDate": "2026-05-01",
    "levelGain": 2,
    "snapshotDate": "2026-05-02",
    "snapshotAt": "2026-05-02T05:22:29.502Z",
    "status": "online",
    "skillHighlights": {
      "distance": {
        "rank": 148,
        "value": 122,
        "label": "Distance Fighting"
      }
    },
    "primaryHighscore": {
      "category": "distance",
      "label": "Distance Fighting",
      "rank": 148,
      "value": 122
    },
    "primarySkillTrend": "none",
    "primarySkillTrendDate": null
  },
  {
    "name": "Claudio Bojanha dois",
    "rank": "Apex Guardian",
    "vocation": "Royal Paladin",
    "level": 701,
    "previousLevel": 699,
    "baselineLevel": 699,
    "baselineDate": "2026-05-01",
    "levelGain": 2,
    "snapshotDate": "2026-05-02",
    "snapshotAt": "2026-05-02T05:22:29.502Z",
    "status": "offline",
    "skillHighlights": {
      "distance": {
        "rank": 124,
        "value": 123,
        "label": "Distance Fighting"
      }
    },
    "primaryHighscore": {
      "category": "distance",
      "label": "Distance Fighting",
      "rank": 124,
      "value": 123
    },
    "primarySkillTrend": "none",
    "primarySkillTrendDate": null
  },
  {
    "name": "Hokage Clarinha",
    "rank": "Apex Guardian",
    "vocation": "Elite Knight",
    "level": 682,
    "previousLevel": 679,
    "baselineLevel": 679,
    "baselineDate": "2026-05-01",
    "levelGain": 3,
    "snapshotDate": "2026-05-02",
    "snapshotAt": "2026-05-02T05:22:29.502Z",
    "status": "offline",
    "skillHighlights": {
      "club": {
        "rank": 78,
        "value": 116,
        "label": "Club Fighting"
      }
    },
    "primaryHighscore": {
      "category": "club",
      "label": "Club Fighting",
      "rank": 78,
      "value": 116
    },
    "primarySkillTrend": "none",
    "primarySkillTrendDate": null
  },
  {
    "name": "Luna Nightwitch",
    "rank": "Apex Guardian",
    "vocation": "Elite Knight",
    "level": 699,
    "previousLevel": 699,
    "baselineLevel": 699,
    "baselineDate": "2026-05-01",
    "levelGain": 0,
    "snapshotDate": "2026-05-02",
    "snapshotAt": "2026-05-02T05:22:29.502Z",
    "status": "offline",
    "skillHighlights": {
      "sword": {
        "rank": 100,
        "value": 118,
        "label": "Sword Fighting"
      }
    },
    "primaryHighscore": {
      "category": "sword",
      "label": "Sword Fighting",
      "rank": 100,
      "value": 118
    },
    "primarySkillTrend": "none",
    "primarySkillTrendDate": null
  },
  {
    "name": "Scorpion Reborn",
    "rank": "Apex Guardian",
    "vocation": "Elite Knight",
    "level": 1074,
    "previousLevel": 1074,
    "baselineLevel": 1074,
    "baselineDate": "2026-05-01",
    "levelGain": 0,
    "snapshotDate": "2026-05-02",
    "snapshotAt": "2026-05-02T05:22:29.502Z",
    "status": "offline",
    "skillHighlights": {
      "axe": {
        "rank": 23,
        "value": 122,
        "label": "Axe Fighting"
      }
    },
    "primaryHighscore": {
      "category": "axe",
      "label": "Axe Fighting",
      "rank": 23,
      "value": 122
    },
    "primarySkillTrend": "none",
    "primarySkillTrendDate": null
  },
  {
    "name": "Seven Madlife",
    "rank": "Apex Guardian",
    "vocation": "Master Sorcerer",
    "level": 687,
    "previousLevel": 687,
    "baselineLevel": 687,
    "baselineDate": "2026-05-01",
    "levelGain": 0,
    "snapshotDate": "2026-05-02",
    "snapshotAt": "2026-05-02T05:22:29.502Z",
    "status": "online",
    "skillHighlights": {
      "magic": {
        "rank": 203,
        "value": 112,
        "label": "Magic Level"
      }
    },
    "primaryHighscore": {
      "category": "magic",
      "label": "Magic Level",
      "rank": 203,
      "value": 112
    },
    "primarySkillTrend": "none",
    "primarySkillTrendDate": null
  },
  {
    "name": "Sir Alonta",
    "rank": "Apex Guardian",
    "vocation": "Elite Knight",
    "level": 774,
    "previousLevel": 774,
    "baselineLevel": 774,
    "baselineDate": "2026-05-01",
    "levelGain": 0,
    "snapshotDate": "2026-05-02",
    "snapshotAt": "2026-05-02T05:22:29.502Z",
    "status": "online",
    "skillHighlights": {
      "axe": {
        "rank": 17,
        "value": 124,
        "label": "Axe Fighting"
      },
      "club": {
        "rank": 31,
        "value": 121,
        "label": "Club Fighting"
      }
    },
    "primaryHighscore": {
      "category": "axe",
      "label": "Axe Fighting",
      "rank": 17,
      "value": 124
    },
    "primarySkillTrend": "none",
    "primarySkillTrendDate": null
  },
  {
    "name": "Skillo da Selva",
    "rank": "Apex Guardian",
    "vocation": "Elder Druid",
    "level": 867,
    "previousLevel": 866,
    "baselineLevel": 866,
    "baselineDate": "2026-05-01",
    "levelGain": 1,
    "snapshotDate": "2026-05-02",
    "snapshotAt": "2026-05-02T05:22:29.502Z",
    "status": "online",
    "skillHighlights": {
      "magic": {
        "rank": 178,
        "value": 114,
        "label": "Magic Level"
      }
    },
    "primaryHighscore": {
      "category": "magic",
      "label": "Magic Level",
      "rank": 178,
      "value": 114
    },
    "primarySkillTrend": "none",
    "primarySkillTrendDate": null
  },
  {
    "name": "Vitinho Cepowisks",
    "rank": "Apex Guardian",
    "vocation": "Elder Druid",
    "level": 788,
    "previousLevel": 786,
    "baselineLevel": 786,
    "baselineDate": "2026-05-01",
    "levelGain": 2,
    "snapshotDate": "2026-05-02",
    "snapshotAt": "2026-05-02T05:22:29.502Z",
    "status": "offline",
    "skillHighlights": {
      "magic": {
        "rank": 142,
        "value": 116,
        "label": "Magic Level"
      }
    },
    "primaryHighscore": {
      "category": "magic",
      "label": "Magic Level",
      "rank": 142,
      "value": 116
    },
    "primarySkillTrend": "none",
    "primarySkillTrendDate": null
  },
  {
    "name": "Asgore Fullagado",
    "rank": "Primal Summoner",
    "vocation": "Paladin",
    "level": 201,
    "previousLevel": 201,
    "baselineLevel": 201,
    "baselineDate": "2026-05-01",
    "levelGain": 0,
    "snapshotDate": "2026-05-02",
    "snapshotAt": "2026-05-02T05:22:29.502Z",
    "status": "offline",
    "skillHighlights": {
      "distance": {
        "rank": 570,
        "value": 115,
        "label": "Distance Fighting"
      }
    },
    "primaryHighscore": {
      "category": "distance",
      "label": "Distance Fighting",
      "rank": 570,
      "value": 115
    },
    "primarySkillTrend": "none",
    "primarySkillTrendDate": null
  },
  {
    "name": "Badlius",
    "rank": "Primal Summoner",
    "vocation": "Master Sorcerer",
    "level": 429,
    "previousLevel": 428,
    "baselineLevel": 428,
    "baselineDate": "2026-05-01",
    "levelGain": 1,
    "snapshotDate": "2026-05-02",
    "snapshotAt": "2026-05-02T05:22:29.502Z",
    "status": "offline",
    "skillHighlights": {
      "magic": {
        "rank": 473,
        "value": 101,
        "label": "Magic Level"
      }
    },
    "primaryHighscore": {
      "category": "magic",
      "label": "Magic Level",
      "rank": 473,
      "value": 101
    },
    "primarySkillTrend": "none",
    "primarySkillTrendDate": null
  },
  {
    "name": "Biscoito Babado",
    "rank": "Primal Summoner",
    "vocation": "Master Sorcerer",
    "level": 362,
    "previousLevel": 362,
    "baselineLevel": 362,
    "baselineDate": "2026-05-01",
    "levelGain": 0,
    "snapshotDate": "2026-05-02",
    "snapshotAt": "2026-05-02T05:22:29.502Z",
    "status": "offline",
    "skillHighlights": {
      "magic": {
        "rank": 600,
        "value": 98,
        "label": "Magic Level"
      }
    },
    "primaryHighscore": {
      "category": "magic",
      "label": "Magic Level",
      "rank": 600,
      "value": 98
    },
    "primarySkillTrend": "none",
    "primarySkillTrendDate": null
  },
  {
    "name": "Bombaschick",
    "rank": "Primal Summoner",
    "vocation": "Elite Knight",
    "level": 229,
    "previousLevel": 229,
    "baselineLevel": 229,
    "baselineDate": "2026-05-01",
    "levelGain": 0,
    "snapshotDate": "2026-05-02",
    "snapshotAt": "2026-05-02T05:22:29.502Z",
    "status": "offline",
    "skillHighlights": {
      "club": {
        "rank": 438,
        "value": 105,
        "label": "Club Fighting"
      }
    },
    "primaryHighscore": {
      "category": "club",
      "label": "Club Fighting",
      "rank": 438,
      "value": 105
    },
    "primarySkillTrend": "none",
    "primarySkillTrendDate": null
  },
  {
    "name": "Daveigavt",
    "rank": "Primal Summoner",
    "vocation": "Royal Paladin",
    "level": 458,
    "previousLevel": 457,
    "baselineLevel": 457,
    "baselineDate": "2026-05-01",
    "levelGain": 1,
    "snapshotDate": "2026-05-02",
    "snapshotAt": "2026-05-02T05:22:29.502Z",
    "status": "offline",
    "skillHighlights": {
      "distance": {
        "rank": 485,
        "value": 116,
        "label": "Distance Fighting"
      }
    },
    "primaryHighscore": {
      "category": "distance",
      "label": "Distance Fighting",
      "rank": 485,
      "value": 116
    },
    "primarySkillTrend": "none",
    "primarySkillTrendDate": null
  },
  {
    "name": "Derekaunn",
    "rank": "Primal Summoner",
    "vocation": "Royal Paladin",
    "level": 249,
    "previousLevel": 249,
    "baselineLevel": 249,
    "baselineDate": "2026-05-01",
    "levelGain": 0,
    "snapshotDate": "2026-05-02",
    "snapshotAt": "2026-05-02T05:22:29.502Z",
    "status": "offline",
    "skillHighlights": {},
    "primaryHighscore": null,
    "primarySkillTrend": "none",
    "primarySkillTrendDate": null
  },
  {
    "name": "Is Maik",
    "rank": "Primal Summoner",
    "vocation": "Elite Knight",
    "level": 380,
    "previousLevel": 373,
    "baselineLevel": 373,
    "baselineDate": "2026-05-01",
    "levelGain": 7,
    "snapshotDate": "2026-05-02",
    "snapshotAt": "2026-05-02T05:22:29.502Z",
    "status": "offline",
    "skillHighlights": {
      "sword": {
        "rank": 162,
        "value": 115,
        "label": "Sword Fighting"
      }
    },
    "primaryHighscore": {
      "category": "sword",
      "label": "Sword Fighting",
      "rank": 162,
      "value": 115
    },
    "primarySkillTrend": "none",
    "primarySkillTrendDate": null
  },
  {
    "name": "Kow Hife",
    "rank": "Primal Summoner",
    "vocation": "Elder Druid",
    "level": 393,
    "previousLevel": 393,
    "baselineLevel": 393,
    "baselineDate": "2026-05-01",
    "levelGain": 0,
    "snapshotDate": "2026-05-02",
    "snapshotAt": "2026-05-02T05:22:29.502Z",
    "status": "online",
    "skillHighlights": {
      "magic": {
        "rank": 694,
        "value": 96,
        "label": "Magic Level"
      }
    },
    "primaryHighscore": {
      "category": "magic",
      "label": "Magic Level",
      "rank": 694,
      "value": 96
    },
    "primarySkillTrend": "none",
    "primarySkillTrendDate": null
  },
  {
    "name": "Liocrismar Junior",
    "rank": "Primal Summoner",
    "vocation": "Elite Knight",
    "level": 264,
    "previousLevel": 264,
    "baselineLevel": 264,
    "baselineDate": "2026-05-01",
    "levelGain": 0,
    "snapshotDate": "2026-05-02",
    "snapshotAt": "2026-05-02T05:22:29.502Z",
    "status": "offline",
    "skillHighlights": {
      "axe": {
        "rank": 350,
        "value": 107,
        "label": "Axe Fighting"
      }
    },
    "primaryHighscore": {
      "category": "axe",
      "label": "Axe Fighting",
      "rank": 350,
      "value": 107
    },
    "primarySkillTrend": "none",
    "primarySkillTrendDate": null
  },
  {
    "name": "Mage Kiro",
    "rank": "Primal Summoner",
    "vocation": "Master Sorcerer",
    "level": 526,
    "previousLevel": 526,
    "baselineLevel": 526,
    "baselineDate": "2026-05-01",
    "levelGain": 0,
    "snapshotDate": "2026-05-02",
    "snapshotAt": "2026-05-02T05:22:29.502Z",
    "status": "offline",
    "skillHighlights": {
      "magic": {
        "rank": 399,
        "value": 103,
        "label": "Magic Level"
      }
    },
    "primaryHighscore": {
      "category": "magic",
      "label": "Magic Level",
      "rank": 399,
      "value": 103
    },
    "primarySkillTrend": "none",
    "primarySkillTrendDate": null
  },
  {
    "name": "Mago Morais",
    "rank": "Primal Summoner",
    "vocation": "Knight",
    "level": 237,
    "previousLevel": 237,
    "baselineLevel": 237,
    "baselineDate": "2026-05-01",
    "levelGain": 0,
    "snapshotDate": "2026-05-02",
    "snapshotAt": "2026-05-02T05:22:29.502Z",
    "status": "offline",
    "skillHighlights": {},
    "primaryHighscore": null,
    "primarySkillTrend": "none",
    "primarySkillTrendDate": null
  },
  {
    "name": "Pods Cre",
    "rank": "Primal Summoner",
    "vocation": "Royal Paladin",
    "level": 404,
    "previousLevel": 404,
    "baselineLevel": 404,
    "baselineDate": "2026-05-01",
    "levelGain": 0,
    "snapshotDate": "2026-05-02",
    "snapshotAt": "2026-05-02T05:22:29.502Z",
    "status": "offline",
    "skillHighlights": {
      "distance": {
        "rank": 761,
        "value": 113,
        "label": "Distance Fighting"
      }
    },
    "primaryHighscore": {
      "category": "distance",
      "label": "Distance Fighting",
      "rank": 761,
      "value": 113
    },
    "primarySkillTrend": "none",
    "primarySkillTrendDate": null
  },
  {
    "name": "Severo Snappee",
    "rank": "Primal Summoner",
    "vocation": "Master Sorcerer",
    "level": 354,
    "previousLevel": 354,
    "baselineLevel": 354,
    "baselineDate": "2026-05-01",
    "levelGain": 0,
    "snapshotDate": "2026-05-02",
    "snapshotAt": "2026-05-02T05:22:29.502Z",
    "status": "offline",
    "skillHighlights": {
      "magic": {
        "rank": 633,
        "value": 97,
        "label": "Magic Level"
      }
    },
    "primaryHighscore": {
      "category": "magic",
      "label": "Magic Level",
      "rank": 633,
      "value": 97
    },
    "primarySkillTrend": "none",
    "primarySkillTrendDate": null
  },
  {
    "name": "Vinks",
    "rank": "Primal Summoner",
    "vocation": "Elite Knight",
    "level": 375,
    "previousLevel": 375,
    "baselineLevel": 375,
    "baselineDate": "2026-05-01",
    "levelGain": 0,
    "snapshotDate": "2026-05-02",
    "snapshotAt": "2026-05-02T05:22:29.502Z",
    "status": "offline",
    "skillHighlights": {
      "axe": {
        "rank": 313,
        "value": 108,
        "label": "Axe Fighting"
      }
    },
    "primaryHighscore": {
      "category": "axe",
      "label": "Axe Fighting",
      "rank": 313,
      "value": 108
    },
    "primarySkillTrend": "none",
    "primarySkillTrendDate": null
  },
  {
    "name": "Witch Nobeta",
    "rank": "Primal Summoner",
    "vocation": "Exalted Monk",
    "level": 308,
    "previousLevel": 308,
    "baselineLevel": 308,
    "baselineDate": "2026-05-01",
    "levelGain": 0,
    "snapshotDate": "2026-05-02",
    "snapshotAt": "2026-05-02T05:22:29.502Z",
    "status": "offline",
    "skillHighlights": {
      "fist": {
        "rank": 397,
        "value": 95,
        "label": "Fist Fighting"
      }
    },
    "primaryHighscore": {
      "category": "fist",
      "label": "Fist Fighting",
      "rank": 397,
      "value": 95
    },
    "primarySkillTrend": "none",
    "primarySkillTrendDate": null
  },
  {
    "name": "Amiane Keny",
    "rank": "Rising Sentinel",
    "vocation": "Royal Paladin",
    "level": 150,
    "previousLevel": 150,
    "baselineLevel": 150,
    "baselineDate": "2026-05-01",
    "levelGain": 0,
    "snapshotDate": "2026-05-02",
    "snapshotAt": "2026-05-02T05:22:29.502Z",
    "status": "offline",
    "skillHighlights": {},
    "primaryHighscore": null,
    "primarySkillTrend": "none",
    "primarySkillTrendDate": null
  },
  {
    "name": "Asgore Lessus",
    "rank": "Rising Sentinel",
    "vocation": "None",
    "level": 2,
    "previousLevel": 2,
    "baselineLevel": 2,
    "baselineDate": "2026-05-01",
    "levelGain": 0,
    "snapshotDate": "2026-05-02",
    "snapshotAt": "2026-05-02T05:22:29.502Z",
    "status": "offline",
    "skillHighlights": {},
    "primaryHighscore": null,
    "primarySkillTrend": "none",
    "primarySkillTrendDate": null
  },
  {
    "name": "Cadu Uzabunnda",
    "rank": "Rising Sentinel",
    "vocation": "Elite Knight",
    "level": 56,
    "previousLevel": 56,
    "baselineLevel": 56,
    "baselineDate": "2026-05-01",
    "levelGain": 0,
    "snapshotDate": "2026-05-02",
    "snapshotAt": "2026-05-02T05:22:29.502Z",
    "status": "offline",
    "skillHighlights": {},
    "primaryHighscore": null,
    "primarySkillTrend": "none",
    "primarySkillTrendDate": null
  },
  {
    "name": "Deyvcabelinho",
    "rank": "Rising Sentinel",
    "vocation": "Master Sorcerer",
    "level": 102,
    "previousLevel": 102,
    "baselineLevel": 102,
    "baselineDate": "2026-05-01",
    "levelGain": 0,
    "snapshotDate": "2026-05-02",
    "snapshotAt": "2026-05-02T05:22:29.502Z",
    "status": "offline",
    "skillHighlights": {},
    "primaryHighscore": null,
    "primarySkillTrend": "none",
    "primarySkillTrendDate": null
  },
  {
    "name": "Dike Fibrado",
    "rank": "Rising Sentinel",
    "vocation": "Elite Knight",
    "level": 38,
    "previousLevel": 38,
    "baselineLevel": 38,
    "baselineDate": "2026-05-01",
    "levelGain": 0,
    "snapshotDate": "2026-05-02",
    "snapshotAt": "2026-05-02T05:22:29.502Z",
    "status": "offline",
    "skillHighlights": {
      "axe": {
        "rank": 313,
        "value": 108,
        "label": "Axe Fighting"
      }
    },
    "primaryHighscore": {
      "category": "axe",
      "label": "Axe Fighting",
      "rank": 313,
      "value": 108
    },
    "primarySkillTrend": "none",
    "primarySkillTrendDate": null
  },
  {
    "name": "Doule Lana",
    "rank": "Rising Sentinel",
    "vocation": "Elite Knight",
    "level": 59,
    "previousLevel": 59,
    "baselineLevel": 59,
    "baselineDate": "2026-05-01",
    "levelGain": 0,
    "snapshotDate": "2026-05-02",
    "snapshotAt": "2026-05-02T05:22:29.502Z",
    "status": "offline",
    "skillHighlights": {
      "axe": {
        "rank": 270,
        "value": 109,
        "label": "Axe Fighting"
      }
    },
    "primaryHighscore": {
      "category": "axe",
      "label": "Axe Fighting",
      "rank": 270,
      "value": 109
    },
    "primarySkillTrend": "none",
    "primarySkillTrendDate": null
  },
  {
    "name": "Ed Galoucura",
    "rank": "Rising Sentinel",
    "vocation": "Druid",
    "level": 8,
    "previousLevel": 8,
    "baselineLevel": 8,
    "baselineDate": "2026-05-01",
    "levelGain": 0,
    "snapshotDate": "2026-05-02",
    "snapshotAt": "2026-05-02T05:22:29.502Z",
    "status": "offline",
    "skillHighlights": {},
    "primaryHighscore": null,
    "primarySkillTrend": "none",
    "primarySkillTrendDate": null
  },
  {
    "name": "Heitor Pay",
    "rank": "Rising Sentinel",
    "vocation": "Master Sorcerer",
    "level": 188,
    "previousLevel": 188,
    "baselineLevel": 188,
    "baselineDate": "2026-05-01",
    "levelGain": 0,
    "snapshotDate": "2026-05-02",
    "snapshotAt": "2026-05-02T05:22:29.502Z",
    "status": "offline",
    "skillHighlights": {},
    "primaryHighscore": null,
    "primarySkillTrend": "none",
    "primarySkillTrendDate": null
  },
  {
    "name": "Isakiinn",
    "rank": "Rising Sentinel",
    "vocation": "Sorcerer",
    "level": 101,
    "previousLevel": 101,
    "baselineLevel": 101,
    "baselineDate": "2026-05-01",
    "levelGain": 0,
    "snapshotDate": "2026-05-02",
    "snapshotAt": "2026-05-02T05:22:29.502Z",
    "status": "offline",
    "skillHighlights": {},
    "primaryHighscore": null,
    "primarySkillTrend": "none",
    "primarySkillTrendDate": null
  },
  {
    "name": "Kyrlor Zuman",
    "rank": "Rising Sentinel",
    "vocation": "Elder Druid",
    "level": 130,
    "previousLevel": 130,
    "baselineLevel": 130,
    "baselineDate": "2026-05-01",
    "levelGain": 0,
    "snapshotDate": "2026-05-02",
    "snapshotAt": "2026-05-02T05:22:29.502Z",
    "status": "offline",
    "skillHighlights": {},
    "primaryHighscore": null,
    "primarySkillTrend": "none",
    "primarySkillTrendDate": null
  },
  {
    "name": "Nonota",
    "rank": "Rising Sentinel",
    "vocation": "Monk",
    "level": 15,
    "previousLevel": 15,
    "baselineLevel": 15,
    "baselineDate": "2026-05-01",
    "levelGain": 0,
    "snapshotDate": "2026-05-02",
    "snapshotAt": "2026-05-02T05:22:29.502Z",
    "status": "offline",
    "skillHighlights": {},
    "primaryHighscore": null,
    "primarySkillTrend": "none",
    "primarySkillTrendDate": null
  },
  {
    "name": "Valeu tamojunto",
    "rank": "Rising Sentinel",
    "vocation": "Elite Knight",
    "level": 164,
    "previousLevel": 164,
    "baselineLevel": 164,
    "baselineDate": "2026-05-01",
    "levelGain": 0,
    "snapshotDate": "2026-05-02",
    "snapshotAt": "2026-05-02T05:22:29.502Z",
    "status": "offline",
    "skillHighlights": {
      "axe": {
        "rank": 190,
        "value": 111,
        "label": "Axe Fighting"
      }
    },
    "primaryHighscore": {
      "category": "axe",
      "label": "Axe Fighting",
      "rank": 190,
      "value": 111
    },
    "primarySkillTrend": "none",
    "primarySkillTrendDate": null
  },
  {
    "name": "Walord Canelinha",
    "rank": "Rising Sentinel",
    "vocation": "Elder Druid",
    "level": 35,
    "previousLevel": 35,
    "baselineLevel": 35,
    "baselineDate": "2026-05-01",
    "levelGain": 0,
    "snapshotDate": "2026-05-02",
    "snapshotAt": "2026-05-02T05:22:29.502Z",
    "status": "offline",
    "skillHighlights": {},
    "primaryHighscore": null,
    "primarySkillTrend": "none",
    "primarySkillTrendDate": null
  },
  {
    "name": "Aezir Silverbloods",
    "rank": "Provisional Soul",
    "vocation": "Knight",
    "level": 30,
    "previousLevel": 24,
    "baselineLevel": 24,
    "baselineDate": "2026-05-01",
    "levelGain": 6,
    "snapshotDate": "2026-05-02",
    "snapshotAt": "2026-05-02T05:22:29.502Z",
    "status": "online",
    "skillHighlights": {},
    "primaryHighscore": null,
    "primarySkillTrend": "none",
    "primarySkillTrendDate": null
  },
  {
    "name": "Amassando Paozin",
    "rank": "Provisional Soul",
    "vocation": "Druid",
    "level": 8,
    "previousLevel": 8,
    "baselineLevel": 8,
    "baselineDate": "2026-05-01",
    "levelGain": 0,
    "snapshotDate": "2026-05-02",
    "snapshotAt": "2026-05-02T05:22:29.502Z",
    "status": "offline",
    "skillHighlights": {},
    "primaryHighscore": null,
    "primarySkillTrend": "none",
    "primarySkillTrendDate": null
  },
  {
    "name": "Ana Katana",
    "rank": "Provisional Soul",
    "vocation": "Master Sorcerer",
    "level": 168,
    "previousLevel": 168,
    "baselineLevel": 168,
    "baselineDate": "2026-05-01",
    "levelGain": 0,
    "snapshotDate": "2026-05-02",
    "snapshotAt": "2026-05-02T05:22:29.502Z",
    "status": "offline",
    "skillHighlights": {},
    "primaryHighscore": null,
    "primarySkillTrend": "none",
    "primarySkillTrendDate": null
  },
  {
    "name": "Arlekinho",
    "rank": "Provisional Soul",
    "vocation": "Master Sorcerer",
    "level": 135,
    "previousLevel": 133,
    "baselineLevel": 133,
    "baselineDate": "2026-05-01",
    "levelGain": 2,
    "snapshotDate": "2026-05-02",
    "snapshotAt": "2026-05-02T05:22:29.502Z",
    "status": "offline",
    "skillHighlights": {},
    "primaryHighscore": null,
    "primarySkillTrend": "none",
    "primarySkillTrendDate": null
  },
  {
    "name": "Atendente do Serasa",
    "rank": "Provisional Soul",
    "vocation": "Elite Knight",
    "level": 221,
    "previousLevel": 213,
    "baselineLevel": 213,
    "baselineDate": "2026-05-01",
    "levelGain": 8,
    "snapshotDate": "2026-05-02",
    "snapshotAt": "2026-05-02T05:22:29.502Z",
    "status": "offline",
    "skillHighlights": {
      "sword": {
        "rank": 356,
        "value": 109,
        "label": "Sword Fighting"
      }
    },
    "primaryHighscore": {
      "category": "sword",
      "label": "Sword Fighting",
      "rank": 356,
      "value": 109
    },
    "primarySkillTrend": "none",
    "primarySkillTrendDate": null
  },
  {
    "name": "Big Monkts",
    "rank": "Provisional Soul",
    "vocation": "Exalted Monk",
    "level": 52,
    "previousLevel": 30,
    "baselineLevel": 30,
    "baselineDate": "2026-05-01",
    "levelGain": 22,
    "snapshotDate": "2026-05-02",
    "snapshotAt": "2026-05-02T05:22:29.502Z",
    "status": "offline",
    "skillHighlights": {
      "fist": {
        "rank": 584,
        "value": 90,
        "label": "Fist Fighting"
      }
    },
    "primaryHighscore": {
      "category": "fist",
      "label": "Fist Fighting",
      "rank": 584,
      "value": 90
    },
    "primarySkillTrend": "none",
    "primarySkillTrendDate": null
  },
  {
    "name": "Brinquedo Rozknat",
    "rank": "Provisional Soul",
    "vocation": "Elite Knight",
    "level": 128,
    "previousLevel": 120,
    "baselineLevel": 120,
    "baselineDate": "2026-05-01",
    "levelGain": 8,
    "snapshotDate": "2026-05-02",
    "snapshotAt": "2026-05-02T05:22:29.502Z",
    "status": "offline",
    "skillHighlights": {},
    "primaryHighscore": null,
    "primarySkillTrend": "none",
    "primarySkillTrendDate": null
  },
  {
    "name": "Dgzika Tankmode",
    "rank": "Provisional Soul",
    "vocation": "Elite Knight",
    "level": 82,
    "previousLevel": 82,
    "baselineLevel": 82,
    "baselineDate": "2026-05-01",
    "levelGain": 0,
    "snapshotDate": "2026-05-02",
    "snapshotAt": "2026-05-02T05:22:29.502Z",
    "status": "offline",
    "skillHighlights": {
      "club": {
        "rank": 140,
        "value": 113,
        "label": "Club Fighting"
      }
    },
    "primaryHighscore": {
      "category": "club",
      "label": "Club Fighting",
      "rank": 140,
      "value": 113
    },
    "primarySkillTrend": "none",
    "primarySkillTrendDate": null
  },
  {
    "name": "Dgzikarp",
    "rank": "Provisional Soul",
    "vocation": "Royal Paladin",
    "level": 150,
    "previousLevel": 139,
    "baselineLevel": 139,
    "baselineDate": "2026-05-01",
    "levelGain": 11,
    "snapshotDate": "2026-05-02",
    "snapshotAt": "2026-05-02T05:22:29.502Z",
    "status": "online",
    "skillHighlights": {
      "distance": {
        "rank": 348,
        "value": 118,
        "label": "Distance Fighting"
      }
    },
    "primaryHighscore": {
      "category": "distance",
      "label": "Distance Fighting",
      "rank": 348,
      "value": 118
    },
    "primarySkillTrend": "none",
    "primarySkillTrendDate": null
  },
  {
    "name": "Edynho",
    "rank": "Provisional Soul",
    "vocation": "Exalted Monk",
    "level": 126,
    "previousLevel": 123,
    "baselineLevel": 123,
    "baselineDate": "2026-05-01",
    "levelGain": 3,
    "snapshotDate": "2026-05-02",
    "snapshotAt": "2026-05-02T05:22:29.502Z",
    "status": "online",
    "skillHighlights": {},
    "primaryHighscore": null,
    "primarySkillTrend": "none",
    "primarySkillTrendDate": null
  },
  {
    "name": "Eo Tiigrao",
    "rank": "Provisional Soul",
    "vocation": "Royal Paladin",
    "level": 227,
    "previousLevel": 223,
    "baselineLevel": 223,
    "baselineDate": "2026-05-01",
    "levelGain": 4,
    "snapshotDate": "2026-05-02",
    "snapshotAt": "2026-05-02T05:22:29.502Z",
    "status": "offline",
    "skillHighlights": {},
    "primaryHighscore": null,
    "primarySkillTrend": "none",
    "primarySkillTrendDate": null
  },
  {
    "name": "Iaguinho Masfrigo",
    "rank": "Provisional Soul",
    "vocation": "Elder Druid",
    "level": 96,
    "previousLevel": 93,
    "baselineLevel": 93,
    "baselineDate": "2026-05-01",
    "levelGain": 3,
    "snapshotDate": "2026-05-02",
    "snapshotAt": "2026-05-02T05:22:29.502Z",
    "status": "online",
    "skillHighlights": {},
    "primaryHighscore": null,
    "primarySkillTrend": "none",
    "primarySkillTrendDate": null
  },
  {
    "name": "Ithan Crow",
    "rank": "Provisional Soul",
    "vocation": "Royal Paladin",
    "level": 255,
    "previousLevel": 256,
    "baselineLevel": 256,
    "baselineDate": "2026-05-01",
    "levelGain": 0,
    "snapshotDate": "2026-05-02",
    "snapshotAt": "2026-05-02T05:22:29.502Z",
    "status": "online",
    "skillHighlights": {
      "distance": {
        "rank": 103,
        "value": 124,
        "label": "Distance Fighting"
      }
    },
    "primaryHighscore": {
      "category": "distance",
      "label": "Distance Fighting",
      "rank": 103,
      "value": 124
    },
    "primarySkillTrend": "none",
    "primarySkillTrendDate": null
  },
  {
    "name": "Jobaz",
    "rank": "Provisional Soul",
    "vocation": "Elite Knight",
    "level": 863,
    "previousLevel": 863,
    "baselineLevel": 863,
    "baselineDate": "2026-05-01",
    "levelGain": 0,
    "snapshotDate": "2026-05-02",
    "snapshotAt": "2026-05-02T05:22:29.502Z",
    "status": "offline",
    "skillHighlights": {
      "sword": {
        "rank": 26,
        "value": 125,
        "label": "Sword Fighting"
      }
    },
    "primaryHighscore": {
      "category": "sword",
      "label": "Sword Fighting",
      "rank": 26,
      "value": 125
    },
    "primarySkillTrend": "none",
    "primarySkillTrendDate": null
  },
  {
    "name": "John Balajohnes",
    "rank": "Provisional Soul",
    "vocation": "Elite Knight",
    "level": 486,
    "previousLevel": 486,
    "baselineLevel": 486,
    "baselineDate": "2026-05-01",
    "levelGain": 0,
    "snapshotDate": "2026-05-02",
    "snapshotAt": "2026-05-02T05:22:29.502Z",
    "status": "offline",
    "skillHighlights": {
      "sword": {
        "rank": 123,
        "value": 117,
        "label": "Sword Fighting"
      }
    },
    "primaryHighscore": {
      "category": "sword",
      "label": "Sword Fighting",
      "rank": 123,
      "value": 117
    },
    "primarySkillTrend": "none",
    "primarySkillTrendDate": null
  },
  {
    "name": "John Ovomaltine",
    "rank": "Provisional Soul",
    "vocation": "Exalted Monk",
    "level": 135,
    "previousLevel": 135,
    "baselineLevel": 135,
    "baselineDate": "2026-05-01",
    "levelGain": 0,
    "snapshotDate": "2026-05-02",
    "snapshotAt": "2026-05-02T05:22:29.502Z",
    "status": "offline",
    "skillHighlights": {
      "fist": {
        "rank": 118,
        "value": 102,
        "label": "Fist Fighting"
      }
    },
    "primaryHighscore": {
      "category": "fist",
      "label": "Fist Fighting",
      "rank": 118,
      "value": 102
    },
    "primarySkillTrend": "none",
    "primarySkillTrendDate": null
  },
  {
    "name": "Lilinha Chickenflymode",
    "rank": "Provisional Soul",
    "vocation": "Royal Paladin",
    "level": 184,
    "previousLevel": 174,
    "baselineLevel": 174,
    "baselineDate": "2026-05-01",
    "levelGain": 10,
    "snapshotDate": "2026-05-02",
    "snapshotAt": "2026-05-02T05:22:29.502Z",
    "status": "online",
    "skillHighlights": {
      "distance": {
        "rank": 891,
        "value": 112,
        "label": "Distance Fighting"
      }
    },
    "primaryHighscore": {
      "category": "distance",
      "label": "Distance Fighting",
      "rank": 891,
      "value": 112
    },
    "primarySkillTrend": "none",
    "primarySkillTrendDate": null
  },
  {
    "name": "Madam Curie",
    "rank": "Provisional Soul",
    "vocation": "Master Sorcerer",
    "level": 477,
    "previousLevel": 477,
    "baselineLevel": 477,
    "baselineDate": "2026-05-01",
    "levelGain": 0,
    "snapshotDate": "2026-05-02",
    "snapshotAt": "2026-05-02T05:22:29.502Z",
    "status": "offline",
    "skillHighlights": {
      "magic": {
        "rank": 429,
        "value": 102,
        "label": "Magic Level"
      }
    },
    "primaryHighscore": {
      "category": "magic",
      "label": "Magic Level",
      "rank": 429,
      "value": 102
    },
    "primarySkillTrend": "none",
    "primarySkillTrendDate": null
  },
  {
    "name": "Marck Tank",
    "rank": "Provisional Soul",
    "vocation": "Knight",
    "level": 15,
    "previousLevel": 15,
    "baselineLevel": 15,
    "baselineDate": "2026-05-01",
    "levelGain": 0,
    "snapshotDate": "2026-05-02",
    "snapshotAt": "2026-05-02T05:22:29.502Z",
    "status": "offline",
    "skillHighlights": {},
    "primaryHighscore": null,
    "primarySkillTrend": "none",
    "primarySkillTrendDate": null
  },
  {
    "name": "Marck The Knight",
    "rank": "Provisional Soul",
    "vocation": "Elite Knight",
    "level": 430,
    "previousLevel": 426,
    "baselineLevel": 426,
    "baselineDate": "2026-05-01",
    "levelGain": 4,
    "snapshotDate": "2026-05-02",
    "snapshotAt": "2026-05-02T05:22:29.502Z",
    "status": "offline",
    "skillHighlights": {
      "axe": {
        "rank": 104,
        "value": 114,
        "label": "Axe Fighting"
      }
    },
    "primaryHighscore": {
      "category": "axe",
      "label": "Axe Fighting",
      "rank": 104,
      "value": 114
    },
    "primarySkillTrend": "none",
    "primarySkillTrendDate": null
  },
  {
    "name": "Marck The Tank",
    "rank": "Provisional Soul",
    "vocation": "Elite Knight",
    "level": 160,
    "previousLevel": 160,
    "baselineLevel": 160,
    "baselineDate": "2026-05-01",
    "levelGain": 0,
    "snapshotDate": "2026-05-02",
    "snapshotAt": "2026-05-02T05:22:29.502Z",
    "status": "offline",
    "skillHighlights": {
      "axe": {
        "rank": 156,
        "value": 112,
        "label": "Axe Fighting"
      }
    },
    "primaryHighscore": {
      "category": "axe",
      "label": "Axe Fighting",
      "rank": 156,
      "value": 112
    },
    "primarySkillTrend": "none",
    "primarySkillTrendDate": null
  },
  {
    "name": "Miiojin",
    "rank": "Provisional Soul",
    "vocation": "Elite Knight",
    "level": 132,
    "previousLevel": 132,
    "baselineLevel": 132,
    "baselineDate": "2026-05-01",
    "levelGain": 0,
    "snapshotDate": "2026-05-02",
    "snapshotAt": "2026-05-02T05:22:29.502Z",
    "status": "offline",
    "skillHighlights": {},
    "primaryHighscore": null,
    "primarySkillTrend": "none",
    "primarySkillTrendDate": null
  },
  {
    "name": "Monk Hopium",
    "rank": "Provisional Soul",
    "vocation": "Exalted Monk",
    "level": 54,
    "previousLevel": 54,
    "baselineLevel": 54,
    "baselineDate": "2026-05-01",
    "levelGain": 0,
    "snapshotDate": "2026-05-02",
    "snapshotAt": "2026-05-02T05:22:29.502Z",
    "status": "offline",
    "skillHighlights": {
      "fist": {
        "rank": 330,
        "value": 97,
        "label": "Fist Fighting"
      }
    },
    "primaryHighscore": {
      "category": "fist",
      "label": "Fist Fighting",
      "rank": 330,
      "value": 97
    },
    "primarySkillTrend": "none",
    "primarySkillTrendDate": null
  },
  {
    "name": "Monk Soberano",
    "rank": "Provisional Soul",
    "vocation": "Monk",
    "level": 20,
    "previousLevel": 20,
    "baselineLevel": 20,
    "baselineDate": "2026-05-01",
    "levelGain": 0,
    "snapshotDate": "2026-05-02",
    "snapshotAt": "2026-05-02T05:22:29.502Z",
    "status": "offline",
    "skillHighlights": {},
    "primaryHighscore": null,
    "primarySkillTrend": "none",
    "primarySkillTrendDate": null
  },
  {
    "name": "Mundica Pobreloko",
    "rank": "Provisional Soul",
    "vocation": "Elite Knight",
    "level": 141,
    "previousLevel": 141,
    "baselineLevel": 141,
    "baselineDate": "2026-05-01",
    "levelGain": 0,
    "snapshotDate": "2026-05-02",
    "snapshotAt": "2026-05-02T05:22:29.502Z",
    "status": "offline",
    "skillHighlights": {},
    "primaryHighscore": null,
    "primarySkillTrend": "none",
    "primarySkillTrendDate": null
  },
  {
    "name": "New Beast",
    "rank": "Provisional Soul",
    "vocation": "Elite Knight",
    "level": 201,
    "previousLevel": 181,
    "baselineLevel": 181,
    "baselineDate": "2026-05-01",
    "levelGain": 20,
    "snapshotDate": "2026-05-02",
    "snapshotAt": "2026-05-02T05:22:29.502Z",
    "status": "offline",
    "skillHighlights": {
      "axe": {
        "rank": 135,
        "value": 113,
        "label": "Axe Fighting"
      }
    },
    "primaryHighscore": {
      "category": "axe",
      "label": "Axe Fighting",
      "rank": 135,
      "value": 113
    },
    "primarySkillTrend": "none",
    "primarySkillTrendDate": null
  },
  {
    "name": "Ogremagi",
    "rank": "Provisional Soul",
    "vocation": "Master Sorcerer",
    "level": 435,
    "previousLevel": 435,
    "baselineLevel": 435,
    "baselineDate": "2026-05-01",
    "levelGain": 0,
    "snapshotDate": "2026-05-02",
    "snapshotAt": "2026-05-02T05:22:29.502Z",
    "status": "online",
    "skillHighlights": {
      "magic": {
        "rank": 741,
        "value": 95,
        "label": "Magic Level"
      }
    },
    "primaryHighscore": {
      "category": "magic",
      "label": "Magic Level",
      "rank": 741,
      "value": 95
    },
    "primarySkillTrend": "none",
    "primarySkillTrendDate": null
  },
  {
    "name": "Razzga Mortalha",
    "rank": "Provisional Soul",
    "vocation": "Royal Paladin",
    "level": 146,
    "previousLevel": 146,
    "baselineLevel": 146,
    "baselineDate": "2026-05-01",
    "levelGain": 0,
    "snapshotDate": "2026-05-02",
    "snapshotAt": "2026-05-02T05:22:29.502Z",
    "status": "offline",
    "skillHighlights": {
      "distance": {
        "rank": 485,
        "value": 116,
        "label": "Distance Fighting"
      }
    },
    "primaryHighscore": {
      "category": "distance",
      "label": "Distance Fighting",
      "rank": 485,
      "value": 116
    },
    "primarySkillTrend": "none",
    "primarySkillTrendDate": null
  },
  {
    "name": "Vellvet Crow",
    "rank": "Provisional Soul",
    "vocation": "Elite Knight",
    "level": 484,
    "previousLevel": 479,
    "baselineLevel": 479,
    "baselineDate": "2026-05-01",
    "levelGain": 5,
    "snapshotDate": "2026-05-02",
    "snapshotAt": "2026-05-02T05:22:29.502Z",
    "status": "online",
    "skillHighlights": {
      "axe": {
        "rank": 350,
        "value": 107,
        "label": "Axe Fighting"
      }
    },
    "primaryHighscore": {
      "category": "axe",
      "label": "Axe Fighting",
      "rank": 350,
      "value": 107
    },
    "primarySkillTrend": "none",
    "primarySkillTrendDate": null
  },
  {
    "name": "Waton Kako",
    "rank": "Provisional Soul",
    "vocation": "Master Sorcerer",
    "level": 384,
    "previousLevel": 384,
    "baselineLevel": 384,
    "baselineDate": "2026-05-01",
    "levelGain": 0,
    "snapshotDate": "2026-05-02",
    "snapshotAt": "2026-05-02T05:22:29.502Z",
    "status": "offline",
    "skillHighlights": {
      "magic": {
        "rank": 694,
        "value": 96,
        "label": "Magic Level"
      }
    },
    "primaryHighscore": {
      "category": "magic",
      "label": "Magic Level",
      "rank": 694,
      "value": 96
    },
    "primarySkillTrend": "none",
    "primarySkillTrendDate": null
  }
]